Metadata-Version: 2.1
Name: noyerTransformer
Version: 0.1.0
Summary: Un convertisseur de fichier .tex en .md pour Mkdocs
Home-page: https://github.com/Elowarp/latexToMkdocs
Author: Elowarp
Author-email: elowarp@gmail.com
License: MIT
